pdgpy/__init__.py
pdgpy-0.1.dist-info/METADATA
pdgpy-0.1.dist-info/WHEEL
pdgpy-0.1.dist-info/top_level.txt
pdgpy-0.1.dist-info/RECORD
