Metadata-Version: 2.1
Name: pdgpy
Version: 0.1
Author-email: name <placeholder@email.com>
Project-URL: Homepage, https://github.com/pdgpy/pdgpy
Project-URL: Bug Tracker, https://github.com/pdgpy/pdgpy/issues
Classifier: Programming Language :: Python :: 3
Classifier: License :: OSI Approved :: MIT License
Classifier: Operating System :: OS Independent
Requires-Python: >=3.7
Requires-Dist: numpy
Requires-Dist: pandas
Requires-Dist: pgmpy
Requires-Dist: matplotlib-venn
Requires-Dist: networkx
Requires-Dist: cvxpy
Requires-Dist: seaborn
